Verilog代码/7_vote(.v
module vote_7in(
input a,b,c,d,e,f,g,
output out
    );
assign out = (a+b+c+d+e+f+g >3)?1:0;
endmodule

Verilog代码/7tb.v
`timescale 1ns / 1ns
`include "7_vote(.v"
module vote_7in_tb;
reg a,b,c,d,e,f,g;
wire out;

vote_7in U1(.a(a),.b(b),.c(c),.d(d),.e(e),.f(f),.g(g),.out(out));

initial 
begin
	$dumpfile("7wave.vcd");
	$dumpvars;
	{a,b,c,d,e,f,g} = 7'b0;
	#5 a = 1'b1;
	#5 b = 1'b1;
	#5 c = 1'b1;
	#5 d = 1'b1;
	#5 e = 1'b1;
	#5 f = 1'b1;
	#5 g = 1'b1;
	#5 $stop;
	$finish;
end
endmodule

Verilog代码/7wave.vcd
$date
	Mon Jun 03 16:13:06 2024
$end
$version
	Icarus Verilog
$end
$timescale
	1ns
$end
$scope module vote_7in_tb $end
$var wire 1 ! out $end
$var reg 1 " a $end
$var reg 1 # b $end
$var reg 1 $ c $end
$var reg 1 % d $end
$var reg 1 & e $end
$var reg 1 ' f $end
$var reg 1 ( g $end
$scope module U1 $end
$var wire 1 " a $end
$var wire 1 # b $end
$var wire 1 $ c $end
$var wire 1 % d $end
$var wire 1 & e $end
$var wire 1 ' f $end
$var wire 1 ( g $end
$var wire 1 ! out $end
$upscope $end
$upscope $end
$enddefinitions $end
$comment Show the parameter values. $end
$dumpall
$end
#0
$dumpvars
0(
0'
0&
0%
0$
0#
0"
0!
$end
#5
1"
#10
1#
#15
1$
#20
1!
1%
#25
1&
#30
1'
#35
1(
