Verilog代码/Time.v
module counter(  
    input clk,  
    input reset,  
    input enable,  
    output reg [3:0] count  
);  
  
    // 如果reset为0，count设置为0；  
    // 如果enable为1，在时钟上升沿，count加1；  
    // 如果enable为0，count不变  
  
    always @(posedge clk or negedge reset)
    begin
        if(reset) 
            begin  
                if(enable)
                    count<=count+1'b1;
            end
            else
                count<=0;
    end  
  
endmodule

Verilog代码/Timetb.v
`timescale  1ns / 1ps
`include "Time.v"
module tb_counter;

// counter Parameters
parameter PERIOD  = 10;


// counter Inputs

reg   reset                                = 0 ;
reg   enable                               = 1 ;

// counter Outputs
wire  [3:0]  count                         ;




counter  u_counter (
  
    .reset                   ( reset         ),
    .enable                  ( enable        ),

    .count                   ( count   [3:0] )
);

initial
begin
    $dumpfile("twave.vcd");
   $dumpvars;
    #2 reset =0;
    #5 reset=1;
    #40 enable=0;
    #41 enable=1;
    #50 reset=0;
    #51 reset=1;
    #6000 $stop;
    $finish;
end
    reg clk;
    initial
        clk=0;
        always #(clk)
        clk=~clk;
        counter ctr(clk,reset,enable,count);
endmodule

Verilog代码/twave.vcd
$date
	Mon Jun 03 17:51:07 2024
$end
$version
	Icarus Verilog
$end
$timescale
	1ps
$end
$scope module tb_counter $end
$var wire 4 ! count [3:0] $end
$var parameter 32 " PERIOD $end
$var reg 1 # clk $end
$var reg 1 $ enable $end
$var reg 1 % reset $end
$scope module ctr $end
$var wire 1 # clk $end
$var wire 1 $ enable $end
$var wire 1 % reset $end
$var reg 4 & count [3:0] $end
$upscope $end
$scope module u_counter $end
$var wire 1 ' clk $end
$var wire 1 $ enable $end
$var wire 1 % reset $end
$var reg 4 ( count [3:0] $end
$upscope $end
$upscope $end
$enddefinitions $end
$comment Show the parameter values. $end
$dumpall
b1010 "
$end
#0
$dumpvars
b0 (
z'
b0 &
0%
1$
1#
b0 !
$end
#1000
1#
#2000
1#
#3000
1#
#4000
1#
#5000
1#
#6000
1#
#7000
b0x !
b1 &
1#
1%
#8000
b0x0 !
b10 &
1#
#9000
b0xx !
b11 &
1#
#10000
b0x00 !
b100 &
1#
#11000
b0x0x !
b101 &
1#
#12000
b0xx0 !
b110 &
1#
#13000
b0xxx !
b111 &
1#
#14000
bx000 !
b1000 &
1#
#15000
bx00x !
b1001 &
1#
#16000
bx0x0 !
b1010 &
1#
#17000
bx0xx !
b1011 &
1#
#18000
bx00 !
b1100 &
1#
#19000
bx0x !
b1101 &
1#
#20000
bx0 !
b1110 &
1#
#21000
bx !
b1111 &
1#
#22000
b0 !
b0 &
1#
#23000
b0x !
b1 &
1#
#24000
b0x0 !
b10 &
1#
#25000
b0xx !
b11 &
1#
#26000
b0x00 !
b100 &
1#
#27000
b0x0x !
b101 &
1#
#28000
b0xx0 !
b110 &
1#
#29000
b0xxx !
b111 &
1#
#30000
bx000 !
b1000 &
1#
#31000
bx00x !
b1001 &
1#
#32000
bx0x0 !
b1010 &
1#
#33000
bx0xx !
b1011 &
1#
#34000
bx00 !
b1100 &
1#
#35000
bx0x !
b1101 &
1#
#36000
bx0 !
b1110 &
1#
#37000
bx !
b1111 &
1#
#38000
b0 !
b0 &
1#
#39000
b0x !
b1 &
1#
#40000
b0x0 !
b10 &
1#
#41000
b0xx !
b11 &
1#
#42000
b0x00 !
b100 &
1#
#43000
b0x0x !
b101 &
1#
#44000
b0xx0 !
b110 &
1#
#45000
b0xxx !
b111 &
1#
#46000
bx000 !
b1000 &
1#
#47000
1#
0$
#48000
1#
#49000
1#
#50000
1#
#51000
1#
#52000
1#
#53000
1#
#54000
1#
#55000
1#
#56000
1#
#57000
1#
#58000
1#
#59000
1#
#60000
1#
#61000
1#
#62000
1#
#63000
1#
#64000
1#
#65000
1#
#66000
1#
#67000
1#
#68000
1#
#69000
1#
#70000
1#
#71000
1#
#72000
1#
#73000
1#
#74000
1#
#75000
1#
#76000
1#
#77000
1#
#78000
1#
#79000
1#
#80000
1#
#81000
1#
#82000
1#
#83000
1#
#84000
1#
#85000
1#
#86000
1#
#87000
1#
#88000
bx00x !
b1001 &
1#
1$
#89000
bx0x0 !
b1010 &
1#
#90000
bx0xx !
b1011 &
1#
#91000
bx00 !
b1100 &
1#
#92000
bx0x !
b1101 &
1#
#93000
bx0 !
b1110 &
1#
#94000
bx !
b1111 &
1#
#95000
b0 !
b0 &
1#
#96000
b0x !
b1 &
1#
#97000
b0x0 !
b10 &
1#
#98000
b0xx !
b11 &
1#
#99000
b0x00 !
b100 &
1#
#100000
b0x0x !
b101 &
1#
#101000
b0xx0 !
b110 &
1#
#102000
b0xxx !
b111 &
1#
#103000
bx000 !
b1000 &
1#
#104000
bx00x !
b1001 &
1#
#105000
bx0x0 !
b1010 &
1#
#106000
bx0xx !
b1011 &
1#
#107000
bx00 !
b1100 &
1#
#108000
bx0x !
b1101 &
1#
#109000
bx0 !
b1110 &
1#
#110000
bx !
b1111 &
1#
#111000
b0 !
b0 &
1#
#112000
b0x !
b1 &
1#
#113000
b0x0 !
b10 &
1#
#114000
b0xx !
b11 &
1#
#115000
b0x00 !
b100 &
1#
#116000
b0x0x !
b101 &
1#
#117000
b0xx0 !
b110 &
1#
#118000
b0xxx !
b111 &
1#
#119000
bx000 !
b1000 &
1#
#120000
bx00x !
b1001 &
1#
#121000
bx0x0 !
b1010 &
1#
#122000
bx0xx !
b1011 &
1#
#123000
bx00 !
b1100 &
1#
#124000
bx0x !
b1101 &
1#
#125000
bx0 !
b1110 &
1#
#126000
bx !
b1111 &
1#
#127000
b0 !
b0 &
1#
#128000
b0x !
b1 &
1#
#129000
b0x0 !
b10 &
1#
#130000
b0xx !
b11 &
1#
#131000
b0x00 !
b100 &
1#
#132000
b0x0x !
b101 &
1#
#133000
b0xx0 !
b110 &
1#
#134000
b0xxx !
b111 &
1#
#135000
bx000 !
b1000 &
1#
#136000
bx00x !
b1001 &
1#
#137000
bx0x0 !
b1010 &
1#
#138000
b0 !
b0 &
1#
0%
